nowpayments/__init__.py
nowpayments/models/__init__.py
nowpayments/models/payment.py
nowpayments/sandbox.py
nowpayments-1.3.3.dist-info/LICENSE
nowpayments-1.3.3.dist-info/WHEEL
nowpayments-1.3.3.dist-info/METADATA
nowpayments-1.3.3.dist-info/RECORD
