Metadata-Version: 2.1
Name: nowpayments
Version: 1.3.3
Summary: A Python wrapper for the NOWPayments API
Home-page: https://github.com/Ventura94/NOWPayments-Python-API
License: MIT
Author: Arian Ventura Rodríguez
Author-email: arianventura94@gmail.com
Requires-Python: >=3.9,<4.0
Classifier: License :: OSI Approved :: MIT License
Classifier: Programming Language :: Python :: 3
Classifier: Programming Language :: Python :: 3.9
Classifier: Programming Language :: Python :: 3.10
Classifier: Programming Language :: Python :: 3.11
Requires-Dist: requests (>=2.28.1,<3.0.0)
Project-URL: Repository, https://github.com/Ventura94/NOWPayments-Python-API
